flow_sdk/__init__.py
flow_sdk/capture/__init__.py
flow_sdk/capture/request.py
flow_sdk/capture/response.py
flow_sdk/derive/__init__.py
flow_sdk/derive/request.py
flow_sdk/derive/response.py
flow_sdk/flow.py
flow_sdk/logger.py
flow_sdk/shim_airbyte_cdk.py
flow_sdk/shim_singer_sdk.py
flow_sdk-0.1.9.dist-info/METADATA
flow_sdk-0.1.9.dist-info/WHEEL
flow_sdk-0.1.9.dist-info/RECORD
