Metadata-Version: 2.1
Name: flow-sdk
Version: 0.1.9
Summary: 
Home-page: https://github.com/estuary/connectors/tree/main/python
Author: Joseph Shearer
Author-email: joseph@estuary.dev
Requires-Python: >=3.11,<3.12
Classifier: Programming Language :: Python :: 3
Classifier: Programming Language :: Python :: 3.11
Requires-Dist: jsonlines (>=4.0.0,<5.0.0)
Requires-Dist: mypy (>=1.5,<2.0)
Requires-Dist: orjson (>=3.9.7,<4.0.0)
Requires-Dist: pydantic (>=1.10,<2.0)
Requires-Dist: pytest (>=7.4.3,<8.0.0)
Requires-Dist: requests (>=2.31.0,<3.0.0)
Requires-Dist: types-requests (>=2.31,<3.0)
